deco_helper/__init__.py
deco_helper/helpers.py
deco_helper-0.1.0.dist-info/METADATA
deco_helper-0.1.0.dist-info/WHEEL
deco_helper-0.1.0.dist-info/top_level.txt
deco_helper-0.1.0.dist-info/RECORD
