Metadata-Version: 2.1
Name: deco-helper
Version: 0.1.0
Summary: Decorator Helper
Home-page: https://github.com/Kcheonwoong/deco_helper
Author: CheonwoongKwak
Author-email: cheonwoong91@gmail.com
License: MIT
Platform: any
Requires-Python: >=3.6
